{"version":1,"resource":"file:///home/sibam/setup-symphony-screensaver.sh","entries":[{"id":"ixFz.sh","source":"Chat Edit: 'I want to replicate the Symphony screensaver. help me to understand it and how to do it also show me the flow of the files and code to do it.\nanalyse all the files given and do it'","timestamp":1768625365128},{"id":"48ou.sh","source":"Chat Edit: 'I want to implement screensaver like Omarchy and Symphony\nthe workflows of the screen saver in text format for both omarchy and symhony are there in the /omarchy folder shared.\nthe original configuration for omarchy screen save is in the ormarchy folder.\nthe original configuration for symphony screen save is in the dotfiles folder shared.\nThe config file of the hyprland which I'm using in the .config folder shared.\nwithout changing the original codes in the .config folder. Help me implement the screensaver like the omarchy and the symphony.\nanalyse the files in detail and tell me if it is possible without any crase in the hyprland I am using '","timestamp":1768627888470}]}